{"nodes": [{"id": "packages_api_src_services_pdf_ts", "label": "pdf.ts", "file_type": "code", "source_file": "packages/api/src/services/pdf.ts", "source_location": "L1"}, {"id": "pdf_escapehtml", "label": "escapeHtml()", "file_type": "code", "source_file": "packages/api/src/services/pdf.ts", "source_location": "L29"}, {"id": "pdf_generatecashreceiptpdf", "label": "generateCashReceiptPdf()", "file_type": "code", "source_file": "packages/api/src/services/pdf.ts", "source_location": "L108"}, {"id": "pdf_generateinvoicepdf", "label": "generateInvoicePdf()", "file_type": "code", "source_file": "packages/api/src/services/pdf.ts", "source_location": "L149"}, {"id": "pdf_renderinvoicewithpdfx", "label": "renderInvoiceWithPdfx()", "file_type": "code", "source_file": "packages/api/src/services/pdf.ts", "source_location": "L188"}, {"id": "pdf_getappurl", "label": "getAppUrl()", "file_type": "code", "source_file": "packages/api/src/services/pdf.ts", "source_location": "L217"}, {"id": "pdf_createinternalrendersignature", "label": "createInternalRenderSignature()", "file_type": "code", "source_file": "packages/api/src/services/pdf.ts", "source_location": "L232"}, {"id": "pdf_getinternalpdfrendersecret", "label": "getInternalPdfRenderSecret()", "file_type": "code", "source_file": "packages/api/src/services/pdf.ts", "source_location": "L243"}, {"id": "pdf_buildreceipthtml", "label": "buildReceiptHtml()", "file_type": "code", "source_file": "packages/api/src/services/pdf.ts", "source_location": "L253"}, {"id": "pdf_renderhtmltopdf", "label": "renderHtmlToPdf()", "file_type": "code", "source_file": "packages/api/src/services/pdf.ts", "source_location": "L377"}, {"id": "pdf_fc", "label": "fc()", "file_type": "code", "source_file": "packages/api/src/services/pdf.ts", "source_location": "L421"}, {"id": "pdf_fmtdate", "label": "fmtDate()", "file_type": "code", "source_file": "packages/api/src/services/pdf.ts", "source_location": "L428"}, {"id": "pdf_fmtdatetime", "label": "fmtDateTime()", "file_type": "code", "source_file": "packages/api/src/services/pdf.ts", "source_location": "L437"}], "edges": [{"source": "packages_api_src_services_pdf_ts", "target": "crypto", "relation": "imports_from", "confidence": "EXTRACTED", "source_file": "packages/api/src/services/pdf.ts", "source_location": "L18", "weight": 1.0}, {"source": "packages_api_src_services_pdf_ts", "target": "packages_api_src_services_supabase_admin", "relation": "imports_from", "confidence": "EXTRACTED", "source_file": "packages/api/src/services/pdf.ts", "source_location": "L19", "weight": 1.0}, {"source": "packages_api_src_services_pdf_ts", "target": "pdf_escapehtml", "relation": "contains", "confidence": "EXTRACTED", "source_file": "packages/api/src/services/pdf.ts", "source_location": "L29", "weight": 1.0}, {"source": "packages_api_src_services_pdf_ts", "target": "pdf_generatecashreceiptpdf", "relation": "contains", "confidence": "EXTRACTED", "source_file": "packages/api/src/services/pdf.ts", "source_location": "L108", "weight": 1.0}, {"source": "packages_api_src_services_pdf_ts", "target": "pdf_generateinvoicepdf", "relation": "contains", "confidence": "EXTRACTED", "source_file": "packages/api/src/services/pdf.ts", "source_location": "L149", "weight": 1.0}, {"source": "packages_api_src_services_pdf_ts", "target": "pdf_renderinvoicewithpdfx", "relation": "contains", "confidence": "EXTRACTED", "source_file": "packages/api/src/services/pdf.ts", "source_location": "L188", "weight": 1.0}, {"source": "packages_api_src_services_pdf_ts", "target": "pdf_getappurl", "relation": "contains", "confidence": "EXTRACTED", "source_file": "packages/api/src/services/pdf.ts", "source_location": "L217", "weight": 1.0}, {"source": "packages_api_src_services_pdf_ts", "target": "pdf_createinternalrendersignature", "relation": "contains", "confidence": "EXTRACTED", "source_file": "packages/api/src/services/pdf.ts", "source_location": "L232", "weight": 1.0}, {"source": "packages_api_src_services_pdf_ts", "target": "pdf_getinternalpdfrendersecret", "relation": "contains", "confidence": "EXTRACTED", "source_file": "packages/api/src/services/pdf.ts", "source_location": "L243", "weight": 1.0}, {"source": "packages_api_src_services_pdf_ts", "target": "pdf_buildreceipthtml", "relation": "contains", "confidence": "EXTRACTED", "source_file": "packages/api/src/services/pdf.ts", "source_location": "L253", "weight": 1.0}, {"source": "packages_api_src_services_pdf_ts", "target": "pdf_renderhtmltopdf", "relation": "contains", "confidence": "EXTRACTED", "source_file": "packages/api/src/services/pdf.ts", "source_location": "L377", "weight": 1.0}, {"source": "packages_api_src_services_pdf_ts", "target": "pdf_fc", "relation": "contains", "confidence": "EXTRACTED", "source_file": "packages/api/src/services/pdf.ts", "source_location": "L421", "weight": 1.0}, {"source": "packages_api_src_services_pdf_ts", "target": "pdf_fmtdate", "relation": "contains", "confidence": "EXTRACTED", "source_file": "packages/api/src/services/pdf.ts", "source_location": "L428", "weight": 1.0}, {"source": "packages_api_src_services_pdf_ts", "target": "pdf_fmtdatetime", "relation": "contains", "confidence": "EXTRACTED", "source_file": "packages/api/src/services/pdf.ts", "source_location": "L437", "weight": 1.0}, {"source": "pdf_generatecashreceiptpdf", "target": "pdf_buildreceipthtml", "relation": "calls", "confidence": "EXTRACTED", "source_file": "packages/api/src/services/pdf.ts", "source_location": "L112", "weight": 1.0}, {"source": "pdf_generatecashreceiptpdf", "target": "pdf_renderhtmltopdf", "relation": "calls", "confidence": "EXTRACTED", "source_file": "packages/api/src/services/pdf.ts", "source_location": "L113", "weight": 1.0}, {"source": "pdf_generateinvoicepdf", "target": "pdf_renderinvoicewithpdfx", "relation": "calls", "confidence": "EXTRACTED", "source_file": "packages/api/src/services/pdf.ts", "source_location": "L153", "weight": 1.0}, {"source": "pdf_renderinvoicewithpdfx", "target": "pdf_getappurl", "relation": "calls", "confidence": "EXTRACTED", "source_file": "packages/api/src/services/pdf.ts", "source_location": "L190", "weight": 1.0}, {"source": "pdf_renderinvoicewithpdfx", "target": "pdf_createinternalrendersignature", "relation": "calls", "confidence": "EXTRACTED", "source_file": "packages/api/src/services/pdf.ts", "source_location": "L199", "weight": 1.0}, {"source": "pdf_createinternalrendersignature", "target": "pdf_getinternalpdfrendersecret", "relation": "calls", "confidence": "EXTRACTED", "source_file": "packages/api/src/services/pdf.ts", "source_location": "L233", "weight": 1.0}, {"source": "pdf_buildreceipthtml", "target": "pdf_fc", "relation": "calls", "confidence": "EXTRACTED", "source_file": "packages/api/src/services/pdf.ts", "source_location": "L275", "weight": 1.0}, {"source": "pdf_buildreceipthtml", "target": "pdf_fmtdatetime", "relation": "calls", "confidence": "EXTRACTED", "source_file": "packages/api/src/services/pdf.ts", "source_location": "L287", "weight": 1.0}, {"source": "pdf_buildreceipthtml", "target": "pdf_escapehtml", "relation": "calls", "confidence": "EXTRACTED", "source_file": "packages/api/src/services/pdf.ts", "source_location": "L292", "weight": 1.0}, {"source": "pdf_buildreceipthtml", "target": "pdf_fmtdate", "relation": "calls", "confidence": "EXTRACTED", "source_file": "packages/api/src/services/pdf.ts", "source_location": "L336", "weight": 1.0}], "raw_calls": [{"caller_nid": "pdf_escapehtml", "callee": "replace", "source_file": "packages/api/src/services/pdf.ts", "source_location": "L30"}, {"caller_nid": "pdf_escapehtml", "callee": "replace", "source_file": "packages/api/src/services/pdf.ts", "source_location": "L30"}, {"caller_nid": "pdf_escapehtml", "callee": "replace", "source_file": "packages/api/src/services/pdf.ts", "source_location": "L30"}, {"caller_nid": "pdf_escapehtml", "callee": "replace", "source_file": "packages/api/src/services/pdf.ts", "source_location": "L30"}, {"caller_nid": "pdf_escapehtml", "callee": "replace", "source_file": "packages/api/src/services/pdf.ts", "source_location": "L30"}, {"caller_nid": "pdf_generatecashreceiptpdf", "callee": "upload", "source_file": "packages/api/src/services/pdf.ts", "source_location": "L117"}, {"caller_nid": "pdf_generatecashreceiptpdf", "callee": "from", "source_file": "packages/api/src/services/pdf.ts", "source_location": "L117"}, {"caller_nid": "pdf_generatecashreceiptpdf", "callee": "getPublicUrl", "source_file": "packages/api/src/services/pdf.ts", "source_location": "L128"}, {"caller_nid": "pdf_generatecashreceiptpdf", "callee": "from", "source_file": "packages/api/src/services/pdf.ts", "source_location": "L128"}, {"caller_nid": "pdf_generateinvoicepdf", "callee": "toLocaleDateString", "source_file": "packages/api/src/services/pdf.ts", "source_location": "L156"}, {"caller_nid": "pdf_generateinvoicepdf", "callee": "toLocaleDateString", "source_file": "packages/api/src/services/pdf.ts", "source_location": "L157"}, {"caller_nid": "pdf_generateinvoicepdf", "callee": "upload", "source_file": "packages/api/src/services/pdf.ts", "source_location": "L160"}, {"caller_nid": "pdf_generateinvoicepdf", "callee": "from", "source_file": "packages/api/src/services/pdf.ts", "source_location": "L160"}, {"caller_nid": "pdf_generateinvoicepdf", "callee": "getPublicUrl", "source_file": "packages/api/src/services/pdf.ts", "source_location": "L171"}, {"caller_nid": "pdf_generateinvoicepdf", "callee": "from", "source_file": "packages/api/src/services/pdf.ts", "source_location": "L171"}, {"caller_nid": "pdf_renderinvoicewithpdfx", "callee": "stringify", "source_file": "packages/api/src/services/pdf.ts", "source_location": "L191"}, {"caller_nid": "pdf_renderinvoicewithpdfx", "callee": "fetch", "source_file": "packages/api/src/services/pdf.ts", "source_location": "L195"}, {"caller_nid": "pdf_renderinvoicewithpdfx", "callee": "text", "source_file": "packages/api/src/services/pdf.ts", "source_location": "L210"}, {"caller_nid": "pdf_renderinvoicewithpdfx", "callee": "from", "source_file": "packages/api/src/services/pdf.ts", "source_location": "L214"}, {"caller_nid": "pdf_renderinvoicewithpdfx", "callee": "arrayBuffer", "source_file": "packages/api/src/services/pdf.ts", "source_location": "L214"}, {"caller_nid": "pdf_getappurl", "callee": "replace", "source_file": "packages/api/src/services/pdf.ts", "source_location": "L219"}, {"caller_nid": "pdf_getappurl", "callee": "replace", "source_file": "packages/api/src/services/pdf.ts", "source_location": "L222"}, {"caller_nid": "pdf_createinternalrendersignature", "callee": "digest", "source_file": "packages/api/src/services/pdf.ts", "source_location": "L238"}, {"caller_nid": "pdf_createinternalrendersignature", "callee": "update", "source_file": "packages/api/src/services/pdf.ts", "source_location": "L238"}, {"caller_nid": "pdf_createinternalrendersignature", "callee": "createHmac", "source_file": "packages/api/src/services/pdf.ts", "source_location": "L238"}, {"caller_nid": "pdf_buildreceipthtml", "callee": "abs", "source_file": "packages/api/src/services/pdf.ts", "source_location": "L277"}, {"caller_nid": "pdf_buildreceipthtml", "callee": "toUpperCase", "source_file": "packages/api/src/services/pdf.ts", "source_location": "L337"}, {"caller_nid": "pdf_buildreceipthtml", "callee": "slice", "source_file": "packages/api/src/services/pdf.ts", "source_location": "L337"}, {"caller_nid": "pdf_buildreceipthtml", "callee": "join", "source_file": "packages/api/src/services/pdf.ts", "source_location": "L348"}, {"caller_nid": "pdf_buildreceipthtml", "callee": "map", "source_file": "packages/api/src/services/pdf.ts", "source_location": "L348"}, {"caller_nid": "pdf_renderhtmltopdf", "callee": "import", "source_file": "packages/api/src/services/pdf.ts", "source_location": "L385"}, {"caller_nid": "pdf_renderhtmltopdf", "callee": "import", "source_file": "packages/api/src/services/pdf.ts", "source_location": "L386"}, {"caller_nid": "pdf_renderhtmltopdf", "callee": "executablePath", "source_file": "packages/api/src/services/pdf.ts", "source_location": "L388"}, {"caller_nid": "pdf_renderhtmltopdf", "callee": "import", "source_file": "packages/api/src/services/pdf.ts", "source_location": "L395"}, {"caller_nid": "pdf_renderhtmltopdf", "callee": "launch", "source_file": "packages/api/src/services/pdf.ts", "source_location": "L401"}, {"caller_nid": "pdf_renderhtmltopdf", "callee": "newPage", "source_file": "packages/api/src/services/pdf.ts", "source_location": "L408"}, {"caller_nid": "pdf_renderhtmltopdf", "callee": "setContent", "source_file": "packages/api/src/services/pdf.ts", "source_location": "L409"}, {"caller_nid": "pdf_renderhtmltopdf", "callee": "pdf", "source_file": "packages/api/src/services/pdf.ts", "source_location": "L410"}, {"caller_nid": "pdf_renderhtmltopdf", "callee": "from", "source_file": "packages/api/src/services/pdf.ts", "source_location": "L411"}, {"caller_nid": "pdf_renderhtmltopdf", "callee": "close", "source_file": "packages/api/src/services/pdf.ts", "source_location": "L413"}, {"caller_nid": "pdf_fc", "callee": "format", "source_file": "packages/api/src/services/pdf.ts", "source_location": "L422"}, {"caller_nid": "pdf_fmtdate", "callee": "toLocaleDateString", "source_file": "packages/api/src/services/pdf.ts", "source_location": "L429"}, {"caller_nid": "pdf_fmtdatetime", "callee": "toLocaleString", "source_file": "packages/api/src/services/pdf.ts", "source_location": "L438"}]}